cooltime_guard/__init__.py
cooltime_guard/guard.py
cooltime_guard/py.typed
cooltime_guard-0.1.0.dist-info/METADATA
cooltime_guard-0.1.0.dist-info/WHEEL
cooltime_guard-0.1.0.dist-info/licenses/LICENSE
cooltime_guard-0.1.0.dist-info/RECORD
