Metadata-Version: 2.4
Name: cooltime-guard
Version: 0.1.0
Summary: Context managers that enforce a minimum cool-down interval between consecutive blocks (sync and asyncio).
Project-URL: Homepage, https://github.com/nakat-t/cooltime-guard-py
Project-URL: Repository, https://github.com/nakat-t/cooltime-guard-py
Project-URL: Issues, https://github.com/nakat-t/cooltime-guard-py/issues
Author-email: nakat-t <armaiti.wizard@gmail.com>
License-Expression: MIT
License-File: LICENSE
Keywords: asyncio,context manager,cooldown,cooltime,debounce,rate limit,synchronization,throttle
Classifier: Development Status :: 4 - Beta
Classifier: License :: OSI Approved :: MIT License
Classifier: Operating System :: OS Independent
Classifier: Programming Language :: Python :: 3
Requires-Python: >=3.10
